dataclass_pprint_repr/__init__.py
dataclass_pprint_repr/dataclass_pprint_repr.py
dataclass_pprint_repr-0.1.2.dist-info/METADATA
dataclass_pprint_repr-0.1.2.dist-info/WHEEL
dataclass_pprint_repr-0.1.2.dist-info/top_level.txt
dataclass_pprint_repr-0.1.2.dist-info/RECORD
